chmpy-1.1.11.dist-info/WHEEL
chmpy-1.1.11.dist-info/top_level.txt
chmpy-1.1.11.dist-info/METADATA
chmpy-1.1.11.dist-info/RECORD
chmpy-1.1.11.dist-info/licenses/LICENSE.txt
chmpy/surface.py
chmpy/__init__.py
chmpy/sampling/_sobol.pyx
chmpy/sampling/_lds.cpython-313-x86_64-linux-musl.so
chmpy/sampling/_lds.pyx
chmpy/sampling/_sobol_parameters.npz
chmpy/sampling/_sobol.cpython-313-x86_64-linux-musl.so
chmpy/sampling/__init__.py
chmpy/subgraphs/carboxylic_acid.gt
chmpy/subgraphs/__init__.py
chmpy/shape/sht.py
chmpy/shape/_invariants.cpython-313-x86_64-linux-musl.so
chmpy/shape/_invariants.pyx
chmpy/shape/shape_descriptors.py
chmpy/shape/spherical_harmonics.py
chmpy/shape/convex_hull.py
chmpy/shape/_sht.cpython-313-x86_64-linux-musl.so
chmpy/shape/_sht.pyx
chmpy/shape/assoc_legendre.py
chmpy/shape/reconstruct.py
chmpy/shape/__init__.py
chmpy/opt/xtb.py
chmpy/opt/gulp.py
chmpy/opt/__init__.py
chmpy/ff/lj_params.json
chmpy/ff/params.py
chmpy/ff/__init__.py
chmpy/descriptors/symmetry_function_ani1.py
chmpy/descriptors/__init__.py
chmpy/ext/crystal.py
chmpy/ext/traj.py
chmpy/ext/charges.py
chmpy/ext/excitations.py
chmpy/ext/ase.py
chmpy/ext/vasp.py
chmpy/ext/cx.py
chmpy/ext/elastic_tensor.py
chmpy/ext/cosmo.py
chmpy/ext/solvation_parameters.py
chmpy/ext/__init__.py
chmpy/mc/_mc_lewiner.pyx
chmpy/mc/_mc.py
chmpy/mc/_mc_lewiner.cpython-313-x86_64-linux-musl.so
chmpy/mc/lookup_tables.py
chmpy/mc/__init__.py
chmpy/fmt/mol2.py
chmpy/fmt/sdf.py
chmpy/fmt/xtb.py
chmpy/fmt/tmol.py
chmpy/fmt/nwchem.py
chmpy/fmt/ase.py
chmpy/fmt/xyz_file.py
chmpy/fmt/vasp.py
chmpy/fmt/cube.py
chmpy/fmt/smiles.py
chmpy/fmt/fchk.py
chmpy/fmt/crystal17.py
chmpy/fmt/gulp.py
chmpy/fmt/cif.py
chmpy/fmt/gmf.py
chmpy/fmt/shelx.py
chmpy/fmt/ascii.py
chmpy/fmt/pdb.py
chmpy/fmt/gen.py
chmpy/fmt/__init__.py
chmpy/fmt/raspa.py
chmpy/fmt/aims.py
chmpy/fmt/grd.py
chmpy/fmt/gaussian_log.py
chmpy/cmd/convert.py
chmpy/cmd/__init__.py
chmpy/crystal/fingerprint.py
chmpy/crystal/space_group.py
chmpy/crystal/crystal.py
chmpy/crystal/unit_cell.py
chmpy/crystal/point_group.py
chmpy/crystal/symmetry_operation.py
