Metadata-Version: 2.4
Name: chmpy
Version: 1.1.11
Summary: Molecules, crystals, promolecule and Hirshfeld surfaces using python.
Author-email: Peter Spackman <peterspackman@fastmail.com>
License-Expression: GPL-3.0-or-later
Project-URL: homepage, https://github.com/peterspackman/chmpy
Project-URL: repository, https://github.com/peterspackman/chmpy
Project-URL: documentation, https://peterspackman.github.io/chmpy/
Requires-Python: >=3.10
License-File: LICENSE.txt
Requires-Dist: numpy>=2.1.2
Requires-Dist: scipy>=1.14.1
Requires-Dist: trimesh>=4.5.0
Requires-Dist: matplotlib>=3.9.2
Requires-Dist: seaborn>=0.13.2
Requires-Dist: Jinja2>=3.1.2
Provides-Extra: graph
Requires-Dist: graph_tool; extra == "graph"
Provides-Extra: docs
Requires-Dist: mkdocs; extra == "docs"
Requires-Dist: mkdocs-material; extra == "docs"
Requires-Dist: mkdocstrings; extra == "docs"
Requires-Dist: mkdocstrings-python; extra == "docs"
Requires-Dist: mkdocs-gen-files; extra == "docs"
Requires-Dist: mkdocs-literate-nav; extra == "docs"
Dynamic: license-file
